crapgpt/__init__.py
crapgpt-0.0.1.dist-info/METADATA
crapgpt-0.0.1.dist-info/WHEEL
crapgpt-0.0.1.dist-info/licenses/LICENSE
crapgpt-0.0.1.dist-info/RECORD
