Metadata-Version: 2.1
Name: crapgpt
Version: 0.0.1
Summary: Fine-tuned LLM to predict aspects of an individual's diet given their microbiome profile
Project-URL: Homepage, https://github.com/arjunkohli0707/crapgpt
Project-URL: Issues, https://github.com/arjunkohli0707/crapgpt/issues
Author-email: Arjun Kohli <a2kohli@ucsd.edu>, Ismail Faiz <ifaiz@ucsd.edu>, Yoto Kim <yok038@ucsd.edu>
License-File: LICENSE
Classifier: License :: OSI Approved :: MIT License
Classifier: Operating System :: OS Independent
Classifier: Programming Language :: Python :: 3
Requires-Python: >=3.8
